Workbook
Name FDD_DATA: Databook!$A$2:$K$13

Sheet Databook
A1: Month | B1: Revenue | C1: COGS | D1: Gross Profit | E1: Operating Expenses | F1: EBITDA (Reported) | G1: AR | H1: AP | I1: Inventory | J1: Debt | K1: Cash | L1: Month2 | M1: Reported EBITDA | N1: Adj 1 (June one-time) | O1: Adj 2 (July normalization) | P1: Adj 3 (Year-end normalization) | Q1: Total Adj | R1: Adjusted EBITDA | S1: NWC | T1: NWC vs Peg | U1: Peg Line
A2: Jan | B2: 1200 | C2: 720 | D2: 480 | E2: 300 | F2: 180 | G2: 250 | H2: 180 | I2: 200 | J2: 900 | K2: 120 | L2: =A2 -> Jan | M2: =F2 -> 180 | N2: =IF(L2="Jun",150,0) -> 0 | O2: =IF(L2="Jul",-50,0) -> 0 | P2: =IF(OR(L2="Nov",L2="Dec"),-30,0) -> 0 | Q2: =N2+O2+P2 -> 0 | R2: =M2+Q2 -> 180 | S2: =G2+I2-H2 -> 270 | T2: =S2-$U$16 -> -54.166667 | U2: =$U$16 -> 324.16667
A3: Feb | B3: 1150 | C3: 700 | D3: 450 | E3: 290 | F3: 160 | G3: 240 | H3: 170 | I3: 195 | J3: 900 | K3: 110 | L3: =A3 -> Feb | M3: =F3 -> 160 | N3: =IF(L3="Jun",150,0) -> 0 | O3: =IF(L3="Jul",-50,0) -> 0 | P3: =IF(OR(L3="Nov",L3="Dec"),-30,0) -> 0 | Q3: =N3+O3+P3 -> 0 | R3: =M3+Q3 -> 160 | S3: =G3+I3-H3 -> 265 | T3: =S3-$U$16 -> -59.166667 | U3: =$U$16 -> 324.16667
A4: Mar | B4: 1300 | C4: 780 | D4: 520 | E4: 310 | F4: 210 | G4: 260 | H4: 190 | I4: 210 | J4: 900 | K4: 130 | L4: =A4 -> Mar | M4: =F4 -> 210 | N4: =IF(L4="Jun",150,0) -> 0 | O4: =IF(L4="Jul",-50,0) -> 0 | P4: =IF(OR(L4="Nov",L4="Dec"),-30,0) -> 0 | Q4: =N4+O4+P4 -> 0 | R4: =M4+Q4 -> 210 | S4: =G4+I4-H4 -> 280 | T4: =S4-$U$16 -> -44.166667 | U4: =$U$16 -> 324.16667
A5: Apr | B5: 1250 | C5: 760 | D5: 490 | E5: 305 | F5: 185 | G5: 255 | H5: 185 | I5: 205 | J5: 900 | K5: 125 | L5: =A5 -> Apr | M5: =F5 -> 185 | N5: =IF(L5="Jun",150,0) -> 0 | O5: =IF(L5="Jul",-50,0) -> 0 | P5: =IF(OR(L5="Nov",L5="Dec"),-30,0) -> 0 | Q5: =N5+O5+P5 -> 0 | R5: =M5+Q5 -> 185 | S5: =G5+I5-H5 -> 275 | T5: =S5-$U$16 -> -49.166667 | U5: =$U$16 -> 324.16667
A6: May | B6: 1400 | C6: 820 | D6: 580 | E6: 320 | F6: 260 | G6: 275 | H6: 200 | I6: 220 | J6: 900 | K6: 140 | L6: =A6 -> May | M6: =F6 -> 260 | N6: =IF(L6="Jun",150,0) -> 0 | O6: =IF(L6="Jul",-50,0) -> 0 | P6: =IF(OR(L6="Nov",L6="Dec"),-30,0) -> 0 | Q6: =N6+O6+P6 -> 0 | R6: =M6+Q6 -> 260 | S6: =G6+I6-H6 -> 295 | T6: =S6-$U$16 -> -29.166667 | U6: =$U$16 -> 324.16667
A7: Jun | B7: 1500 | C7: 880 | D7: 620 | E7: 500 | F7: 120 | G7: 300 | H7: 210 | I7: 260 | J7: 900 | K7: 150 | L7: =A7 -> Jun | M7: =F7 -> 120 | N7: =IF(L7="Jun",150,0) -> 150 | O7: =IF(L7="Jul",-50,0) -> 0 | P7: =IF(OR(L7="Nov",L7="Dec"),-30,0) -> 0 | Q7: =N7+O7+P7 -> 150 | R7: =M7+Q7 -> 270 | S7: =G7+I7-H7 -> 350 | T7: =S7-$U$16 -> 25.833333 | U7: =$U$16 -> 324.16667
A8: Jul | B8: 1550 | C8: 900 | D8: 650 | E8: 330 | F8: 320 | G8: 310 | H8: 220 | I8: 240 | J8: 900 | K8: 160 | L8: =A8 -> Jul | M8: =F8 -> 320 | N8: =IF(L8="Jun",150,0) -> 0 | O8: =IF(L8="Jul",-50,0) -> -50 | P8: =IF(OR(L8="Nov",L8="Dec"),-30,0) -> 0 | Q8: =N8+O8+P8 -> -50 | R8: =M8+Q8 -> 270 | S8: =G8+I8-H8 -> 330 | T8: =S8-$U$16 -> 5.8333333 | U8: =$U$16 -> 324.16667
A9: Aug | B9: 1480 | C9: 870 | D9: 610 | E9: 325 | F9: 285 | G9: 305 | H9: 215 | I9: 235 | J9: 900 | K9: 155 | L9: =A9 -> Aug | M9: =F9 -> 285 | N9: =IF(L9="Jun",150,0) -> 0 | O9: =IF(L9="Jul",-50,0) -> 0 | P9: =IF(OR(L9="Nov",L9="Dec"),-30,0) -> 0 | Q9: =N9+O9+P9 -> 0 | R9: =M9+Q9 -> 285 | S9: =G9+I9-H9 -> 325 | T9: =S9-$U$16 -> 0.83333333 | U9: =$U$16 -> 324.16667
A10: Sep | B10: 1600 | C10: 950 | D10: 650 | E10: 340 | F10: 310 | G10: 320 | H10: 230 | I10: 250 | J10: 900 | K10: 165 | L10: =A10 -> Sep | M10: =F10 -> 310 | N10: =IF(L10="Jun",150,0) -> 0 | O10: =IF(L10="Jul",-50,0) -> 0 | P10: =IF(OR(L10="Nov",L10="Dec"),-30,0) -> 0 | Q10: =N10+O10+P10 -> 0 | R10: =M10+Q10 -> 310 | S10: =G10+I10-H10 -> 340 | T10: =S10-$U$16 -> 15.833333 | U10: =$U$16 -> 324.16667
A11: Oct | B11: 1700 | C11: 1000 | D11: 700 | E11: 350 | F11: 350 | G11: 340 | H11: 240 | I11: 260 | J11: 900 | K11: 180 | L11: =A11 -> Oct | M11: =F11 -> 350 | N11: =IF(L11="Jun",150,0) -> 0 | O11: =IF(L11="Jul",-50,0) -> 0 | P11: =IF(OR(L11="Nov",L11="Dec"),-30,0) -> 0 | Q11: =N11+O11+P11 -> 0 | R11: =M11+Q11 -> 350 | S11: =G11+I11-H11 -> 360 | T11: =S11-$U$16 -> 35.833333 | U11: =$U$16 -> 324.16667
A12: Nov | B12: 1800 | C12: 1050 | D12: 750 | E12: 360 | F12: 390 | G12: 360 | H12: 260 | I12: 280 | J12: 900 | K12: 200 | L12: =A12 -> Nov | M12: =F12 -> 390 | N12: =IF(L12="Jun",150,0) -> 0 | O12: =IF(L12="Jul",-50,0) -> 0 | P12: =IF(OR(L12="Nov",L12="Dec"),-30,0) -> -30 | Q12: =N12+O12+P12 -> -30 | R12: =M12+Q12 -> 360 | S12: =G12+I12-H12 -> 380 | T12: =S12-$U$16 -> 55.833333 | U12: =$U$16 -> 324.16667
A13: Dec | B13: 2000 | C13: 1200 | D13: 800 | E13: 370 | F13: 430 | G13: 400 | H13: 300 | I13: 320 | J13: 900 | K13: 250 | L13: =A13 -> Dec | M13: =F13 -> 430 | N13: =IF(L13="Jun",150,0) -> 0 | O13: =IF(L13="Jul",-50,0) -> 0 | P13: =IF(OR(L13="Nov",L13="Dec"),-30,0) -> -30 | Q13: =N13+O13+P13 -> -30 | R13: =M13+Q13 -> 400 | S13: =G13+I13-H13 -> 420 | T13: =S13-$U$16 -> 95.833333 | U13: =$U$16 -> 324.16667
N15: EBITDA Bridge | U15: NWC Peg
N16: Reported EBITDA | O16: =SUM(M2:M13) -> 3200 | U16: =AVERAGE(S2:S13) -> 324.16667
N17: Total Adjustments | O17: =SUM(Q2:Q13) -> 40
N18: Adjusted EBITDA | O18: =O16+O17 -> 3240
N20: Net Debt
N21: Debt | O21: =AVERAGE(J2:J13) -> 900
N22: Cash | O22: =AVERAGE(K2:K13) -> 157.08333
N23: Less: Restricted Cash | O23: =50 -> 50
N24: Adjusted Cash | O24: =O22-O23 -> 107.08333
N25: Net Debt | O25: =O21-O24 -> 792.91667
N28: Deal Summary
N29: Adjusted EBITDA | O29: =O18 -> 3240
N30: Net Debt | O30: =O25 -> 792.91667
N31: NWC Peg | O31: =U16 -> 324.16667
N32: Latest NWC (Dec) | O32: =S13 -> 420
N33: NWC vs Peg (Dec) | O33: =O32-O31 -> 95.833333
N35: Key Insights
N36: Insight 1 (Earnings Quality)
N37: EBITDA required normalization due to one-off cost in June and inflated performance in July and year-end, resulting in a stable adjusted earnings profile.
N38: Insight 2 (Working Capital Risk)
N39: Working capital builds significantly in Q4, with December ~100 above peg, indicating potential cash retention risk for the buyer.
N40: Insight 3 (Deal Impact)
N41: Elevated NWC at closing would likely lead to downward purchase price adjustment unless normalized to peg level.

Sheet FDD_Calculations
B2: Month | C2: Reported EBITDA | D2: Adj 1 (June one-time) | E2: Adj 2 (July normalization) | F2: Adj 3 (Year-end normalization) | G2: Total Adj | H2: Adjusted EBITDA | J2: Revenue
B3: =Databook!A2 -> Jan | C3: =Databook!F2 -> 180 | D3: 0 | E3: 0 | F3: 0 | G3: =SUM(D3:F3) -> 0 | H3: =C3+G3 -> 180 | J3: =Databook!B2 -> 1200
B4: =Databook!A3 -> Feb | C4: =Databook!F3 -> 160 | D4: 0 | E4: 0 | F4: 0 | G4: =SUM(D4:F4) -> 0 | H4: =C4+G4 -> 160 | J4: =Databook!B3 -> 1150
B5: =Databook!A4 -> Mar | C5: =Databook!F4 -> 210 | D5: 0 | E5: 0 | F5: 0 | G5: =SUM(D5:F5) -> 0 | H5: =C5+G5 -> 210 | J5: =Databook!B4 -> 1300
B6: =Databook!A5 -> Apr | C6: =Databook!F5 -> 185 | D6: 0 | E6: 0 | F6: 0 | G6: =SUM(D6:F6) -> 0 | H6: =C6+G6 -> 185 | J6: =Databook!B5 -> 1250
B7: =Databook!A6 -> May | C7: =Databook!F6 -> 260 | D7: 0 | E7: 0 | F7: 0 | G7: =SUM(D7:F7) -> 0 | H7: =C7+G7 -> 260 | J7: =Databook!B6 -> 1400
B8: =Databook!A7 -> Jun | C8: =Databook!F7 -> 120 | D8: 150 | E8: 0 | F8: 0 | G8: =SUM(D8:F8) -> 150 | H8: =C8+G8 -> 270 | J8: =Databook!B7 -> 1500
B9: =Databook!A8 -> Jul | C9: =Databook!F8 -> 320 | D9: 0 | E9: -50 | F9: 0 | G9: =SUM(D9:F9) -> -50 | H9: =C9+G9 -> 270 | J9: =Databook!B8 -> 1550
B10: =Databook!A9 -> Aug | C10: =Databook!F9 -> 285 | D10: 0 | E10: 0 | F10: 0 | G10: =SUM(D10:F10) -> 0 | H10: =C10+G10 -> 285 | J10: =Databook!B9 -> 1480
B11: =Databook!A10 -> Sep | C11: =Databook!F10 -> 310 | D11: 0 | E11: 0 | F11: 0 | G11: =SUM(D11:F11) -> 0 | H11: =C11+G11 -> 310 | J11: =Databook!B10 -> 1600
B12: =Databook!A11 -> Oct | C12: =Databook!F11 -> 350 | D12: 0 | E12: 0 | F12: 0 | G12: =SUM(D12:F12) -> 0 | H12: =C12+G12 -> 350 | J12: =Databook!B11 -> 1700
B13: =Databook!A12 -> Nov | C13: =Databook!F12 -> 390 | D13: 0 | E13: 0 | F13: -30 | G13: =SUM(D13:F13) -> -30 | H13: =C13+G13 -> 360 | J13: =Databook!B12 -> 1800
B14: =Databook!A13 -> Dec | C14: =Databook!F13 -> 430 | D14: 0 | E14: 0 | F14: -30 | G14: =SUM(D14:F14) -> -30 | H14: =C14+G14 -> 400 | J14: =Databook!B13 -> 2000
G15: LTM Adjusted EBITDA | H15: =SUM(H3:H14) -> 3240
B17: Net Debt | C17: Value
B18: Debt | C18: =Databook!J13 -> 900
B19: Less: Cash | C19: =Databook!K13 -> 250
B20: Add: Restricted Cash | C20: 50
B21: Adjusted Net Debt | C21: =C18-C19+C20 -> 700
B24: Month | C24: AR | D24: Inventory | E24: AP | F24: NWC | G24: NWC Peg | H24: NWC vs Peg
B25: =Databook!A2 -> Jan | C25: =Databook!G2 -> 250 | D25: =Databook!I2 -> 200 | E25: =Databook!H2 -> 180 | F25: =C25+D25-E25 -> 270 | G25: =AVERAGE($F$25:$F$36) -> 324.16667 | H25: =F25-G25 -> -54.166667
B26: =Databook!A3 -> Feb | C26: =Databook!G3 -> 240 | D26: =Databook!I3 -> 195 | E26: =Databook!H3 -> 170 | F26: =C26+D26-E26 -> 265 | G26: =AVERAGE($F$25:$F$36) -> 324.16667 | H26: =F26-G26 -> -59.166667
B27: =Databook!A4 -> Mar | C27: =Databook!G4 -> 260 | D27: =Databook!I4 -> 210 | E27: =Databook!H4 -> 190 | F27: =C27+D27-E27 -> 280 | G27: =AVERAGE($F$25:$F$36) -> 324.16667 | H27: =F27-G27 -> -44.166667
B28: =Databook!A5 -> Apr | C28: =Databook!G5 -> 255 | D28: =Databook!I5 -> 205 | E28: =Databook!H5 -> 185 | F28: =C28+D28-E28 -> 275 | G28: =AVERAGE($F$25:$F$36) -> 324.16667 | H28: =F28-G28 -> -49.166667
B29: =Databook!A6 -> May | C29: =Databook!G6 -> 275 | D29: =Databook!I6 -> 220 | E29: =Databook!H6 -> 200 | F29: =C29+D29-E29 -> 295 | G29: =AVERAGE($F$25:$F$36) -> 324.16667 | H29: =F29-G29 -> -29.166667
B30: =Databook!A7 -> Jun | C30: =Databook!G7 -> 300 | D30: =Databook!I7 -> 260 | E30: =Databook!H7 -> 210 | F30: =C30+D30-E30 -> 350 | G30: =AVERAGE($F$25:$F$36) -> 324.16667 | H30: =F30-G30 -> 25.833333
B31: =Databook!A8 -> Jul | C31: =Databook!G8 -> 310 | D31: =Databook!I8 -> 240 | E31: =Databook!H8 -> 220 | F31: =C31+D31-E31 -> 330 | G31: =AVERAGE($F$25:$F$36) -> 324.16667 | H31: =F31-G31 -> 5.8333333
B32: =Databook!A9 -> Aug | C32: =Databook!G9 -> 305 | D32: =Databook!I9 -> 235 | E32: =Databook!H9 -> 215 | F32: =C32+D32-E32 -> 325 | G32: =AVERAGE($F$25:$F$36) -> 324.16667 | H32: =F32-G32 -> 0.83333333
B33: =Databook!A10 -> Sep | C33: =Databook!G10 -> 320 | D33: =Databook!I10 -> 250 | E33: =Databook!H10 -> 230 | F33: =C33+D33-E33 -> 340 | G33: =AVERAGE($F$25:$F$36) -> 324.16667 | H33: =F33-G33 -> 15.833333
B34: =Databook!A11 -> Oct | C34: =Databook!G11 -> 340 | D34: =Databook!I11 -> 260 | E34: =Databook!H11 -> 240 | F34: =C34+D34-E34 -> 360 | G34: =AVERAGE($F$25:$F$36) -> 324.16667 | H34: =F34-G34 -> 35.833333
B35: =Databook!A12 -> Nov | C35: =Databook!G12 -> 360 | D35: =Databook!I12 -> 280 | E35: =Databook!H12 -> 260 | F35: =C35+D35-E35 -> 380 | G35: =AVERAGE($F$25:$F$36) -> 324.16667 | H35: =F35-G35 -> 55.833333
B36: =Databook!A13 -> Dec | C36: =Databook!G13 -> 400 | D36: =Databook!I13 -> 320 | E36: =Databook!H13 -> 300 | F36: =C36+D36-E36 -> 420 | G36: =AVERAGE($F$25:$F$36) -> 324.16667 | H36: =F36-G36 -> 95.833333

Sheet Dashboard
A1: Financial Due Diligence (FDD) Mini Case – Deal Summary Model
B22: Deal Summary
B23: LTM Adjusted EBITDA | C23: =FDD_Calculations!H15 -> 3240
B24: Adjusted Net Debt | C24: =FDD_Calculations!C21 -> 700
B25: Closing NWC Variance | C25: =FDD_Calculations!H36 -> 95.833333
B30: Valuation Bridge (Assumes 6.0x Multiple)
B31: Enterprise Value | C31: =C23*6 -> 19440
B32: Less: Adjusted Net Debt | C32: =C24 -> 700
B33: Add: NWC Adjustment | C33: =C25 -> 95.833333
B34: Implied Equity Value | C34: =C31-C32+C33 -> 18835.833
